preston_new/__init__.py
preston_new/cache.py
preston_new/preston.py
Preston_new-4.2.0.dist-info/LICENSE
Preston_new-4.2.0.dist-info/METADATA
Preston_new-4.2.0.dist-info/WHEEL
Preston_new-4.2.0.dist-info/top_level.txt
Preston_new-4.2.0.dist-info/RECORD
